mocy/__init__.py
mocy/exceptions.py
mocy/request.py
mocy/response.py
mocy/spider.py
mocy/utils.py
mocy/middlewares/__init__.py
mocy/middlewares/random_useragent.py
mocy/middlewares/useragents.txt
mocy-0.2.3.dist-info/METADATA
mocy-0.2.3.dist-info/WHEEL
mocy-0.2.3.dist-info/top_level.txt
mocy-0.2.3.dist-info/RECORD
