Metadata-Version: 2.1
Name: mocy
Version: 0.2.3
Summary: A lightweight web crawling framework.
Home-page: https://github.com/cymoo/mocy
Author: cymoo
Author-email: wakenee@hotmail.com
License: MIT
Keywords: scrapy crawler spider
Platform: any
Classifier: Development Status :: 4 - Beta
Classifier: Operating System :: OS Independent
Classifier: Intended Audience :: Developers
Classifier: License :: OSI Approved :: MIT License
Classifier: Programming Language :: Python :: 3
Classifier: Programming Language :: Python :: 3.6
Classifier: Programming Language :: Python :: 3.7
Classifier: Programming Language :: Python :: 3.8
Classifier: Programming Language :: Python :: 3.9
Classifier: Topic :: Utilities
Classifier: Topic :: Internet :: WWW/HTTP
Classifier: Topic :: Software Development :: Libraries :: Application Frameworks
Classifier: Topic :: Software Development :: Libraries :: Python Modules
Requires-Python: >=3.6
Requires-Dist: requests (>=2.25.1)
Requires-Dist: beautifulsoup4 (>=4.9.3)
Provides-Extra: dev
Requires-Dist: pytest ; extra == 'dev'
